pgdata/__init__.py
pgdata/cli.py
pgdata/database.py
pgdata/table.py
pgdata/util.py
pgdata-0.0.12.dist-info/LICENSE.txt
pgdata-0.0.12.dist-info/METADATA
pgdata-0.0.12.dist-info/WHEEL
pgdata-0.0.12.dist-info/entry_points.txt
pgdata-0.0.12.dist-info/top_level.txt
pgdata-0.0.12.dist-info/RECORD
