Metadata-Version: 2.1
Name: pgdata
Version: 0.0.12
Summary: Postgresql shortcuts
Home-page: https://github.com/smnorris/pgdata
Author: Simon Norris
Author-email: snorris@hillcrestgeo.ca
License: MIT
Keywords: postgresql postgis shortcuts data BC ogr2ogr gdal gis
Platform: UNKNOWN
Classifier: Development Status :: 3 - Alpha
Classifier: Intended Audience :: Developers
Classifier: License :: OSI Approved :: MIT License
Classifier: Operating System :: OS Independent
Classifier: Programming Language :: Python :: 2.7
Classifier: Programming Language :: Python :: 3.3
Classifier: Programming Language :: Python :: 3.4
Classifier: Programming Language :: Python :: 3.5
Classifier: Programming Language :: Python :: 3.6
Requires-Dist: psycopg2-binary
Requires-Dist: sqlalchemy
Requires-Dist: sqlalchemy-utils
Requires-Dist: geoalchemy2
Requires-Dist: alembic
Provides-Extra: test
Requires-Dist: pytest ; extra == 'test'
Requires-Dist: coverage ; extra == 'test'
Requires-Dist: fiona ; extra == 'test'
